MANIFEST.in
setup.py
ris/__init__.py
ris.clickatellhttp.egg-info/PKG-INFO
ris.clickatellhttp.egg-info/SOURCES.txt
ris.clickatellhttp.egg-info/dependency_links.txt
ris.clickatellhttp.egg-info/top_level.txt
ris/clickatellhttp/__init__.py
ris/clickatellhttp/http.py