Metadata-Version: 1.1
Name: ris.clickatellhttp
Version: 0.0.5
Summary: Python implementation of the HTTP API for Clickatell SMS gateway
Home-page: https://github.com/rwizi/clickatellhttp
Author: Rwizi Information Systems
Author-email: norman@ris.co.zw
License: Apache
Keywords: ris clickatell sms gateway
Platform: UNKNOWN
Classifier: Development Status :: 4 - Beta
Classifier: Intended Audience :: Developers
Classifier: Topic :: Communications
Classifier: License :: OSI Approved :: Apache Software License
Classifier: Programming Language :: Python :: 2
Classifier: Programming Language :: Python :: 2.6
Classifier: Programming Language :: Python :: 2.7
